zim_id/__init__.py
zim_id/zim_id.py
zim_id-0.1.0.dist-info/licenses/LICENSE
zim_id-0.1.0.dist-info/METADATA
zim_id-0.1.0.dist-info/WHEEL
zim_id-0.1.0.dist-info/top_level.txt
zim_id-0.1.0.dist-info/RECORD
