Metadata-Version: 2.4
Name: zim_id
Version: 0.1.0
Summary: Zim-ID is a Python library/API for validating, debugging, and generating Zimbabwean national ID numbers.
Author-email: "Haripo Wesley T." <haripowesleyt@proton.me>
Maintainer-email: "Haripo Wesley T." <haripowesleyt@proton.me>
License: MIT License
Project-URL: Homepage, https://github.com/haripowesleyt/zim-id
Project-URL: Issues, https://github.com/haripowesleyt/zim-id/issues
Project-URL: Repository, https://github.com/haripowesleyt/zim-id
Keywords: zimbabwe national id numbers
Classifier: Development Status :: 5 - Production/Stable
Classifier: Intended Audience :: Developers
Classifier: Programming Language :: Python :: 3.7
Classifier: Programming Language :: Python :: 3.8
Classifier: Programming Language :: Python :: 3.9
Classifier: Programming Language :: Python :: 3.10
Classifier: Programming Language :: Python :: 3.11
Classifier: Programming Language :: Python :: 3.12
Classifier: Programming Language :: Python :: 3.13
Classifier: License :: OSI Approved :: MIT License
Classifier: Operating System :: OS Independent
Requires-Python: >=3.7
License-File: LICENSE
Dynamic: license-file
